nuclia/__init__.py
nuclia/config.py
nuclia/data.py
nuclia/decorators.py
nuclia/exceptions.py
nuclia/py.typed
nuclia/cli/__init__.py
nuclia/cli/run.py
nuclia/cli/utils.py
nuclia/lib/__init__.py
nuclia/lib/conversations.py
nuclia/lib/kb.py
nuclia/lib/models.py
nuclia/lib/nua.py
nuclia/lib/nua_chat.py
nuclia/lib/nua_responses.py
nuclia/lib/utils.py
nuclia/sdk/__init__.py
nuclia/sdk/accounts.py
nuclia/sdk/agent.py
nuclia/sdk/auth.py
nuclia/sdk/backup.py
nuclia/sdk/export_import.py
nuclia/sdk/extract_strategy.py
nuclia/sdk/kb.py
nuclia/sdk/kbs.py
nuclia/sdk/logger.py
nuclia/sdk/logs.py
nuclia/sdk/nua.py
nuclia/sdk/nucliadb.py
nuclia/sdk/predict.py
nuclia/sdk/process.py
nuclia/sdk/remi.py
nuclia/sdk/resource.py
nuclia/sdk/search.py
nuclia/sdk/split_strategy.py
nuclia/sdk/task.py
nuclia/sdk/upload.py
nuclia/sdk/zones.py
nuclia/tests/__init__.py
nuclia/tests/conftest.py
nuclia/tests/fixtures.py
nuclia/tests/utils.py
nuclia/tests/assets/conversation.json
nuclia/tests/test_kb/test_backup.py
nuclia/tests/test_kb/test_configuration.py
nuclia/tests/test_kb/test_conversation.py
nuclia/tests/test_kb/test_export_import.py
nuclia/tests/test_kb/test_extract_strategies.py
nuclia/tests/test_kb/test_graph.py
nuclia/tests/test_kb/test_labels.py
nuclia/tests/test_kb/test_logs.py
nuclia/tests/test_kb/test_remi.py
nuclia/tests/test_kb/test_resource.py
nuclia/tests/test_kb/test_search.py
nuclia/tests/test_kb/test_split_strategies.py
nuclia/tests/test_kb/test_tasks.py
nuclia/tests/test_manage/__init__.py
nuclia/tests/test_manage/test_account.py
nuclia/tests/test_manage/test_auth.py
nuclia/tests/test_manage/test_kb.py
nuclia/tests/test_nua/__init__.py
nuclia/tests/test_nua/test_agent.py
nuclia/tests/test_nua/test_predict.py
nuclia/tests/test_nucliadb/__init__.py
nuclia/tests/test_nucliadb/test_crud.py
nuclia/tests/unit/__init__.py
nuclia/tests/unit/test_config.py
nuclia/tests/unit/test_export_import.py
nuclia/tests/unit/test_nua_responses.py
nuclia-4.9.12.dist-info/licenses/LICENSE
nuclia-4.9.12.dist-info/METADATA
nuclia-4.9.12.dist-info/WHEEL
nuclia-4.9.12.dist-info/entry_points.txt
nuclia-4.9.12.dist-info/top_level.txt
nuclia-4.9.12.dist-info/RECORD
