Metadata-Version: 2.4
Name: nuclia
Version: 4.9.12
Summary: Nuclia Python SDK
Author-email: Nuclia <info@nuclia.com>
License-Expression: MIT
Project-URL: Homepage, https://nuclia.com
Project-URL: Repository, https://github.com/nuclia/nuclia.py
Project-URL: Slack, https://join.slack.com/t/nuclia-community/shared_invite/zt-2ldfznncw-LW6GJjOicdEA18kgI~95Xw
Classifier: Development Status :: 4 - Beta
Classifier: Intended Audience :: Developers
Classifier: Intended Audience :: Information Technology
Classifier: Programming Language :: Python
Classifier: Programming Language :: Python :: 3.9
Classifier: Programming Language :: Python :: 3.10
Classifier: Programming Language :: Python :: 3 :: Only
Requires-Python: <4,>=3.9
License-File: LICENSE
Requires-Dist: fire
Requires-Dist: pydantic>=2.0.0
Requires-Dist: pyyaml>=5.4
Requires-Dist: requests
Requires-Dist: httpx
Requires-Dist: httpcore>=1.0.0
Requires-Dist: prompt_toolkit
Requires-Dist: nucliadb_sdk<7,>=6.7.2
Requires-Dist: nucliadb_models<7,>=6.9.0
Requires-Dist: nuclia-models>=0.50.1
Requires-Dist: tqdm
Requires-Dist: aiofiles
Requires-Dist: backoff
Requires-Dist: deprecated
Requires-Dist: tabulate
Provides-Extra: litellm
Requires-Dist: litellm; extra == "litellm"
Provides-Extra: protos
Requires-Dist: nucliadb_protos<7,>=6.4; extra == "protos"
Dynamic: license-file
